./.gitignore
./PKG-INFO
./README.md
./__init__.py
./cluster_embeddings.py
./pyproject.toml
./test.py
feluda_cluster_embeddings-0.2.0.dist-info/METADATA
feluda_cluster_embeddings-0.2.0.dist-info/WHEEL
feluda_cluster_embeddings-0.2.0.dist-info/RECORD
